notion_to_llms_txt/__init__.py
notion_to_llms_txt/generator.py
notion_to_llms_txt/main.py
notion_to_llms_txt/models.py
notion_to_llms_txt/parser.py
notion_to_llms_txt/py.typed
notion_to_llms_txt-0.1.1.dist-info/METADATA
notion_to_llms_txt-0.1.1.dist-info/WHEEL
notion_to_llms_txt-0.1.1.dist-info/entry_points.txt
notion_to_llms_txt-0.1.1.dist-info/licenses/LICENSE
notion_to_llms_txt-0.1.1.dist-info/RECORD
