Metadata-Version: 2.4
Name: notion-to-llms-txt
Version: 0.1.1
Summary: Convert Notion exports to LLMS.txt format for AI agents
Author-email: Tomoaki Nakamura <tomoaki.nakamura@elyza.ai>
License: Apache-2.0
License-File: LICENSE
Keywords: ai,documentation,export,llms,markdown,notion
Classifier: Development Status :: 4 - Beta
Classifier: Intended Audience :: Developers
Classifier: License :: OSI Approved :: Apache Software License
Classifier: Programming Language :: Python :: 3.11
Classifier: Programming Language :: Python :: 3.12
Classifier: Programming Language :: Python :: 3.13
Classifier: Topic :: Documentation
Classifier: Topic :: Text Processing :: Markup
Classifier: Topic :: Utilities
Requires-Python: >=3.11
Requires-Dist: pydantic>=2.0.0
Requires-Dist: rich>=13.0.0
Requires-Dist: typer>=0.12.0
Provides-Extra: dev
Requires-Dist: pytest>=8.0.0; extra == 'dev'
Requires-Dist: ruff>=0.1.0; extra == 'dev'
